pull/__init__.py
pull/main_pull.py
pull/pull_service.py
push/__init__.py
push/main_push.py
push/push_service.py
viais_cli-0.1.0.dist-info/METADATA
viais_cli-0.1.0.dist-info/WHEEL
viais_cli-0.1.0.dist-info/entry_points.txt
viais_cli-0.1.0.dist-info/top_level.txt
viais_cli-0.1.0.dist-info/RECORD
