Metadata-Version: 2.4
Name: viais-cli
Version: 0.1.0
Summary: CLI tool for ViAIF pull-push service
Author: Your Name
Author-email: your.email@example.com
Requires-Python: >=3.13
Requires-Dist: click>=8.0
Dynamic: author
Dynamic: author-email
Dynamic: requires-dist
Dynamic: requires-python
Dynamic: summary
